.gitignore
MANIFEST.in
README.rst
archetypes.linguakeywordwidget-configure.zcml
bootstrap.py
buildout.cfg
setup.py
archetypes/__init__.py
archetypes.linguakeywordwidget.egg-info/PKG-INFO
archetypes.linguakeywordwidget.egg-info/SOURCES.txt
archetypes.linguakeywordwidget.egg-info/dependency_links.txt
archetypes.linguakeywordwidget.egg-info/entry_points.txt
archetypes.linguakeywordwidget.egg-info/namespace_packages.txt
archetypes.linguakeywordwidget.egg-info/not-zip-safe
archetypes.linguakeywordwidget.egg-info/requires.txt
archetypes.linguakeywordwidget.egg-info/top_level.txt
archetypes/linguakeywordwidget/__init__.py
archetypes/linguakeywordwidget/config.py
archetypes/linguakeywordwidget/configure.zcml
archetypes/linguakeywordwidget/demo.py
archetypes/linguakeywordwidget/rebuild_i18n.sh
archetypes/linguakeywordwidget/testing.py
archetypes/linguakeywordwidget/testing.zcml
archetypes/linguakeywordwidget/widget.py
archetypes/linguakeywordwidget/locales/archetypes.linguakeywordwidget.pot
archetypes/linguakeywordwidget/locales/en/LC_MESSAGES/archetypes.linguakeywordwidget.po
archetypes/linguakeywordwidget/locales/fr/LC_MESSAGES/archetypes.linguakeywordwidget.po
archetypes/linguakeywordwidget/profiles/default/metadata.xml
archetypes/linguakeywordwidget/profiles/default/skins.xml
archetypes/linguakeywordwidget/profiles/sample_types/archetype_tool.xml
archetypes/linguakeywordwidget/profiles/sample_types/metadata.xml
archetypes/linguakeywordwidget/profiles/sample_types/types.xml
archetypes/linguakeywordwidget/profiles/sample_types/types/RefBrowserDemo.xml
archetypes/linguakeywordwidget/skins/linguakeywordwidget/getLinguaKeywords.py
archetypes/linguakeywordwidget/skins/linguakeywordwidget/getLinguaKeywordsFromValue.py
archetypes/linguakeywordwidget/skins/linguakeywordwidget/linguakeyword.pt
archetypes/linguakeywordwidget/tests/__init__.py
archetypes/linguakeywordwidget/tests/base.py
archetypes/linguakeywordwidget/tests/test_linguakeyword.py
archetypes/linguakeywordwidget/tests/test_setup.py
archetypes/linguakeywordwidget/upgrades/__init__.py
archetypes/linguakeywordwidget/upgrades/configure.zcml
archetypes/linguakeywordwidget/upgrades/v1x.py
docs/HISTORY.txt