Metadata-Version: 1.0
Name: archetypes.linguakeywordwidget
Version: 1.1
Summary: Archetypes keyword widget with multilanguage support
Home-page: https://github.com/toutpt/archetypes.linguakeywordwidget
Author: JeanMichel FRANCOIS aka toutpt
Author-email: toutpt@gmail.com
License: ZPL 2.1
Keywords: Plone multilanguage keywords widget archetypes
Platform: UNKNOWN
Classifier: Programming Language :: Python
Classifier: Framework :: Plone
Classifier: Framework :: Plone :: 4.0
Classifier: Framework :: Plone :: 4.1
Classifier: Framework :: Plone :: 4.2
